MANIFEST.in
README.rst
setup.py
docs/conf.py
docs/index.rst
xbob/__init__.py
xbob.db.gbu.egg-info/PKG-INFO
xbob.db.gbu.egg-info/SOURCES.txt
xbob.db.gbu.egg-info/dependency_links.txt
xbob.db.gbu.egg-info/entry_points.txt
xbob.db.gbu.egg-info/namespace_packages.txt
xbob.db.gbu.egg-info/not-zip-safe
xbob.db.gbu.egg-info/requires.txt
xbob.db.gbu.egg-info/top_level.txt
xbob/db/__init__.py
xbob/db/gbu/__init__.py
xbob/db/gbu/create.py
xbob/db/gbu/db.sql3
xbob/db/gbu/driver.py
xbob/db/gbu/models.py
xbob/db/gbu/query.py
xbob/db/gbu/test.py