Metadata-Version: 1.1
Name: xbob.db.gbu
Version: 1.2.0
Summary: Database Access API of the Good, the Bad and the Ugly (GBU) image database for Bob
Home-page: http://github.com/bioidiap/xbob.db.gbu
Author: Manuel Guenther
Author-email: manuel.guenther@idiap.ch
License: GPLv3
Platform: UNKNOWN
Classifier: Development Status :: 4 - Beta
Classifier: Intended Audience :: Developers
Classifier: License :: OSI Approved :: GNU General Public License v3 (GPLv3)
Classifier: Natural Language :: English
Classifier: Programming Language :: Python
Classifier: Programming Language :: Python :: 3
Classifier: Topic :: Scientific/Engineering :: Artificial Intelligence
Classifier: Topic :: Database :: Front-Ends
